{
  "main": {
    "id": "362ecb1135c93e2a",
    "type": "split",
    "children": [
      {
        "id": "d272b0f276e55c71",
        "type": "tabs",
        "children": [
          {
            "id": "517fd060c007e250",
            "type": "leaf",
            "state": {
              "type": "markdown",
              "state": {
                "file": "random things.md",
                "mode": "source",
                "source": false
              },
              "icon": "lucide-file",
              "title": "random things"
            }
          }
        ]
      }
    ],
    "direction": "vertical"
  },
  "left": {
    "id": "393687fa30499af7",
    "type": "split",
    "children": [
      {
        "id": "8cca3d842ab4506a",
        "type": "tabs",
        "children": [
          {
            "id": "98655f73a90241b0",
            "type": "leaf",
            "state": {
              "type": "file-explorer",
              "state": {
                "sortOrder": "alphabetical",
                "autoReveal": false
              },
              "icon": "lucide-folder-closed",
              "title": "Files"
            }
          },
          {
            "id": "2cbc6869c4dd94bd",
            "type": "leaf",
            "state": {
              "type": "search",
              "state": {
                "query": "",
                "matchingCase": false,
                "explainSearch": false,
                "collapseAll": false,
                "extraContext": false,
                "sortOrder": "alphabetical"
              },
              "icon": "lucide-search",
              "title": "Search"
            }
          },
          {
            "id": "172b66f11fb138cf",
            "type": "leaf",
            "state": {
              "type": "bookmarks",
              "state": {},
              "icon": "lucide-bookmark",
              "title": "Bookmarks"
            }
          }
        ]
      }
    ],
    "direction": "horizontal",
    "width": 294.5
  },
  "right": {
    "id": "1801ec6dddd1d243",
    "type": "split",
    "children": [
      {
        "id": "634dd39ec72b31a4",
        "type": "tabs",
        "children": [
          {
            "id": "9b9444bb95dc2ccd",
            "type": "leaf",
            "state": {
              "type": "backlink",
              "state": {
                "file": "Web Application Penetration Testing/Reset Password Vulnerabilites.md",
                "collapseAll": false,
                "extraContext": false,
                "sortOrder": "alphabetical",
                "showSearch": false,
                "searchQuery": "",
                "backlinkCollapsed": false,
                "unlinkedCollapsed": true
              },
              "icon": "links-coming-in",
              "title": "Backlinks for Reset Password Vulnerabilites"
            }
          },
          {
            "id": "26d8a620b8fb5f76",
            "type": "leaf",
            "state": {
              "type": "outgoing-link",
              "state": {
                "file": "Web Application Penetration Testing/Reset Password Vulnerabilites.md",
                "linksCollapsed": false,
                "unlinkedCollapsed": true
              },
              "icon": "links-going-out",
              "title": "Outgoing links from Reset Password Vulnerabilites"
            }
          },
          {
            "id": "14512c319d8b4995",
            "type": "leaf",
            "state": {
              "type": "tag",
              "state": {
                "sortOrder": "frequency",
                "useHierarchy": true,
                "showSearch": false,
                "searchQuery": ""
              },
              "icon": "lucide-tags",
              "title": "Tags"
            }
          },
          {
            "id": "d7dc6faa51dfb613",
            "type": "leaf",
            "state": {
              "type": "outline",
              "state": {
                "file": "Web Application Penetration Testing/Reset Password Vulnerabilites.md",
                "followCursor": false,
                "showSearch": false,
                "searchQuery": ""
              },
              "icon": "lucide-list",
              "title": "Outline of Reset Password Vulnerabilites"
            }
          }
        ]
      }
    ],
    "direction": "horizontal",
    "width": 200,
    "collapsed": true
  },
  "left-ribbon": {
    "hiddenItems": {
      "obsidian-git:Open Git source control": false,
      "switcher:Open quick switcher": false,
      "graph:Open graph view": false,
      "canvas:Create new canvas": false,
      "daily-notes:Open today's daily note": false,
      "templates:Insert template": false,
      "command-palette:Open command palette": false
    }
  },
  "active": "517fd060c007e250",
  "lastOpenFiles": [
    "Web Application Penetration Testing/Attachments/Pasted image 20250702005345.png",
    "Web Application Penetration Testing/2FA Vulnerabilites.md",
    "Web Application Penetration Testing/Attachments/Pasted image 20250702104346.png",
    "Web Application Penetration Testing/Attachments/Pasted image 20250702104304.png",
    "Web Application Penetration Testing/Attachments/Pasted image 20250702104141.png",
    "Web Application Penetration Testing/Attachments/Pasted image 20250702104041.png",
    "Web Application Penetration Testing/Attachments/Pasted image 20250702103811.png",
    "Web Application Penetration Testing/Attachments/Pasted image 20250702103458.png",
    "Web Application Penetration Testing/Attachments/Pasted image 20250702103338.png",
    "Web Application Penetration Testing/Attachments/Pasted image 20250702103136.png",
    "Web Application Penetration Testing/Attachments/Pasted image 20250702103123.png",
    "Web Application Penetration Testing/Attachments/Pasted image 20250702103100.png",
    "Web Application Penetration Testing/Reset Password Vulnerabilites.md",
    "Web Application Penetration Testing/Login Vulnerabilites.md",
    "Web Application Penetration Testing/HTML Injection.md",
    "Web Application Penetration Testing/Registration Vulnerabilities.md",
    "Programming languages/Python.md",
    "Web Application Penetration Testing/SSRF/SSRF.md",
    "Web Application Penetration Testing/Click Jacking.md",
    "Web/Web Basics.md",
    "Web Application Penetration Testing/CSRF/CSRF (XSRF).md",
    "Web Application Penetration Testing/CSRF/Advanced CSRF.md",
    "Web Application Penetration Testing/CORS/!CORS Hacking.md",
    "Web/DNS.md",
    "Web Application Penetration Testing/SSRF/Attachments",
    "Web Application Penetration Testing/SSRF",
    "Web Application Penetration Testing/CORS/CORS Advanced.md",
    "random things.md",
    "Web Application Penetration Testing/CORS/Attachments",
    "Web Application Penetration Testing/CORS",
    "HackerRank Task.md",
    "javafx project.md",
    "Kali linux notes/Linux.md",
    "Web Application Penetration Testing/XSS/XSS Reflected.md",
    "random things",
    "Web Application Penetration Testing/CSRF/attachments",
    "Web Application Penetration Testing/CSRF",
    "Web Application Penetration Testing/XSS/XSS Advanced.md",
    "Web Application Penetration Testing/XSS/XSS Stored.md",
    "Web Application Penetration Testing/XSS/XSS Exploit.md",
    "Web Application Penetration Testing/XSS/Swagger Ui XSS and image upload XSS.md",
    "Web Application Penetration Testing/XSS/XSS DOM.md",
    "Web Application Penetration Testing/XSS/attachments",
    "Web Application Penetration Testing/XSS",
    "Burpsuite/Burpsuite 4.md",
    "Burpsuite/Attachments"
  ]
}